utsam/__init__.py
utsam/bases/__init__.py
utsam/bases/assignments.py
utsam/bases/criterias.py
utsam/bases/employees.py
utsam/bases/grades.py
utsam/bases/marking.py
utsam/bases/params.py
utsam/bases/sessions.py
utsam/bases/students.py
utsam/bases/subcriterias.py
utsam/bases/tutors.py
utsam/dbs/__init__.py
utsam/dbs/engines.py
utsam/dbs/postgres.py
utsam/dbs/schemas/__init__.py
utsam/dbs/schemas/masterdata/__init__.py
utsam/dbs/schemas/masterdata/assignments.py
utsam/dbs/schemas/masterdata/courses.py
utsam/dbs/schemas/masterdata/criterias.py
utsam/dbs/schemas/masterdata/employees.py
utsam/dbs/schemas/masterdata/grades.py
utsam/dbs/schemas/masterdata/semesters.py
utsam/dbs/schemas/masterdata/sessions.py
utsam/dbs/schemas/masterdata/students.py
utsam/dbs/schemas/masterdata/subcriterias.py
utsam/dbs/schemas/transactions/__init__.py
utsam/dbs/schemas/transactions/assignment_criteria_student_scores.py
utsam/dbs/schemas/transactions/assignment_student_scores.py
utsam/dbs/schemas/transactions/assignment_subcriteria_grade.py
utsam/dbs/schemas/transactions/assignment_subcriteria_student_scores.py
utsam/dbs/schemas/views/__init__.py
utsam/entities/assignment_criterias.py
utsam/entities/assignment_groups.py
utsam/entities/assignment_subcriteria_grades.py
utsam/entities/assignment_subcriterias.py
utsam/entities/assignments.py
utsam/entities/courses.py
utsam/entities/employees.py
utsam/entities/grades.py
utsam/entities/semesters.py
utsam/entities/sessions.py
utsam/entities/student_groups.py
utsam/entities/students.py
utsam/render/ipython.py
utsam-0.1.40.dist-info/METADATA
utsam-0.1.40.dist-info/WHEEL
utsam-0.1.40.dist-info/RECORD
