Metadata-Version: 2.1
Name: utsam
Version: 0.1.40
Summary: UTS Assignment Marking Package
License: Proprietary License
Author: Your Name
Author-email: you@example.com
Requires-Python: >=3.10,<3.11
Classifier: License :: Other/Proprietary License
Classifier: Programming Language :: Python :: 3
Classifier: Programming Language :: Python :: 3.10
Requires-Dist: Faker (==26.0.0)
Requires-Dist: SQLAlchemy (==2.0.32)
Requires-Dist: altair (==4.2.2)
Requires-Dist: pandas (==2.1.1)
Requires-Dist: pendulum (==3.0.0)
Requires-Dist: pydantic (==2.10.6)
